[
  {
    "url": "https://www.onet.pl/",
    "words": [
      { "text": "w", "count": 157 },
      { "text": "na", "count": 114 },
      { "text": "z", "count": 111 },
      { "text": "i", "count": 64 },
      { "text": "o", "count": 58 },
      { "text": "do", "count": 55 },
      { "text": "długoterminowa", "count": 49 },
      { "text": "pogoda", "count": 37 },
      { "text": "się", "count": 28 },
      { "text": "euro", "count": 27 },
      { "text": "mołdawią", "count": 27 },
      { "text": "to", "count": 26 },
      { "text": "walczymy", "count": 25 },
      { "text": "stadionie", "count": 25 },
      { "text": "pkw", "count": 25 },
      { "text": "narodowym", "count": 25 },
      { "text": "nie", "count": 23 },
      { "text": "function", "count": 22 },
      { "text": "solid", "count": 20 },
      { "text": "dla", "count": 20 }
    ]
  },
  {
    "url": "https://www.fly4free.com/",
    "words": [
      { "text": "from", "count": 36 },
      { "text": "for", "count": 22 },
      { "text": "in", "count": 18 },
      { "text": "to", "count": 15 },
      { "text": "the", "count": 15 },
      { "text": "deals", "count": 11 },
      { "text": "flights", "count": 11 },
      { "text": "our", "count": 10 },
      { "text": "and", "count": 9 },
      { "text": "you", "count": 9 },
      { "text": "important", "count": 9 },
      { "text": "hotel", "count": 8 },
      { "text": "double", "count": 7 },
      { "text": "on", "count": 6 },
      { "text": "website", "count": 6 },
      { "text": "flyfreecom", "count": 6 },
      { "text": "of", "count": 6 },
      { "text": "city", "count": 6 },
      { "text": "pp", "count": 5 },
      { "text": "wellrated", "count": 5 }
    ]
  },
  {
    "url": "https://spidersweb.pl/",
    "words": [
      { "text": "w", "count": 412 },
      { "text": "na", "count": 355 },
      { "text": "października", "count": 265 },
      { "text": "i", "count": 236 },
      { "text": "to", "count": 213 },
      { "text": "do", "count": 198 },
      { "text": "się", "count": 197 },
      { "text": "z", "count": 187 },
      { "text": "nie", "count": 152 },
      { "text": "tech", "count": 134 },
      { "text": "jest", "count": 109 },
      { "text": "jak", "count": 95 },
      { "text": "ale", "count": 77 },
      { "text": "co", "count": 76 },
      { "text": "a", "count": 61 },
      { "text": "czy", "count": 60 },
      { "text": "że", "count": 54 },
      { "text": "po", "count": 53 },
      { "text": "za", "count": 53 },
      { "text": "aktualizacja", "count": 50 }
    ]
  },
  {
    "url": "https://www.wp.pl/",
    "words": [
      { "text": "w", "count": 221 },
      { "text": "na", "count": 116 },
      { "text": "z", "count": 104 },
      { "text": "px", "count": 98 },
      { "text": "i", "count": 88 },
      { "text": "się", "count": 85 },
      { "text": "var", "count": 72 },
      { "text": "do", "count": 71 },
      { "text": "nie", "count": 69 },
      { "text": "autosc", "count": 57 },
      { "text": "media", "count": 51 },
      { "text": "jest", "count": 51 },
      { "text": "undefined", "count": 48 },
      { "text": "automsgridrowgridrow", "count": 46 },
      { "text": "to", "count": 43 },
      { "text": "o", "count": 43 },
      { "text": "true", "count": 34 },
      { "text": "if", "count": 33 },
      { "text": "ms", "count": 32 },
      { "text": "co", "count": 30 }
    ]
  },
  {
    "url": "https://www.skyscanner.pl/",
    "words": [
      { "text": "agent", "count": 23 },
      { "text": "instanceof", "count": 23 },
      { "text": "to", "count": 17 },
      { "text": "new", "count": 15 },
      { "text": "a", "count": 14 },
      { "text": "not", "count": 13 },
      { "text": "the", "count": 13 },
      { "text": "is", "count": 12 },
      { "text": "failed", "count": 11 },
      { "text": "api", "count": 11 },
      { "text": "extends", "count": 11 },
      { "text": "an", "count": 11 },
      { "text": "currently", "count": 11 },
      { "text": "in", "count": 11 },
      { "text": "feature", "count": 10 },
      { "text": "objects", "count": 9 },
      { "text": "require", "count": 9 },
      { "text": "errorall", "count": 9 },
      { "text": "type", "count": 8 },
      { "text": "gstatic", "count": 8 }
    ]
  },
  {
    "url": "https://travelfree.info/",
    "words": [
      { "text": "flights", "count": 30 },
      { "text": "to", "count": 22 },
      { "text": "from", "count": 22 },
      { "text": "px", "count": 20 },
      { "text": "freetab", "count": 20 },
      { "text": "rgb", "count": 18 },
      { "text": "for", "count": 17 },
      { "text": "rtab", "count": 16 },
      { "text": "function", "count": 15 },
      { "text": "by", "count": 14 },
      { "text": "var", "count": 14 },
      { "text": "in", "count": 13 },
      { "text": "free", "count": 13 },
      { "text": "on", "count": 13 },
      { "text": "code", "count": 12 },
      { "text": "width", "count": 12 },
      { "text": "promo", "count": 12 },
      { "text": "pad", "count": 12 },
      { "text": "height", "count": 12 },
      { "text": "posted", "count": 11 }
    ]
  },
  {
    "url": "https://websensa.com/en/back-end-developer-2/",
    "words": [
      { "text": "px", "count": 31 },
      { "text": "and", "count": 24 },
      { "text": "the", "count": 23 },
      { "text": "of", "count": 20 },
      { "text": "to", "count": 18 },
      { "text": "c", "count": 18 },
      { "text": "rgb", "count": 18 },
      { "text": "for", "count": 15 },
      { "text": "dnduploadstatus", "count": 15 },
      { "text": "our", "count": 15 },
      { "text": "cookies", "count": 14 },
      { "text": "a", "count": 13 },
      { "text": "your", "count": 12 },
      { "text": "we", "count": 12 },
      { "text": "in", "count": 12 },
      { "text": "var", "count": 12 },
      { "text": "dnduploaddetails", "count": 12 },
      { "text": "are", "count": 11 },
      { "text": "is", "count": 10 },
      { "text": "important", "count": 10 }
    ]
  }
]

